bestlog/__init__.py
bestlog/__version__.py
bestlog/logger.py
bestlog-1.2.1.dist-info/LICENSE
bestlog-1.2.1.dist-info/METADATA
bestlog-1.2.1.dist-info/WHEEL
bestlog-1.2.1.dist-info/top_level.txt
bestlog-1.2.1.dist-info/RECORD
