Metadata-Version: 2.1
Name: bestlog
Version: 1.2.1
Summary: a simple python logger that logs to file and stdout
Home-page: https://github.com/encoderlee/bestlog
Author: encoderlee
Author-email: encoderlee@gmail.com
License: MIT
Platform: UNKNOWN
Classifier: Programming Language :: Python :: 3
Classifier: License :: OSI Approved :: MIT License
Classifier: Operating System :: OS Independent
License-File: LICENSE
